RISC-V_PE/ALU.v
//Modelo de la ALU de 32 bits para procesamiento de las funciones
`define DEBUG

module alu(
           input        clk,      // Clock input
           input [31:0] A, B,     // ALU 32-bit Inputs                 
           input [4:0]  ALU_Sel,  // ALU Selection
           output reg [31:0] ALU_Out, // ALU 32-bit Output
           output reg Zero,        // Zero flag when ALU output is 0
           output reg ALUcomplete  // Indicates end of operation
    );
    integer i;
    reg [31:0] y;
    wire [32:0] tmp;

    always @(posedge clk) begin
        ALUcomplete <= 0; // Indicates operation is in progress
        case (ALU_Sel)
            5'b00000: // Addition
               ALU_Out <= A + B; 
            5'b00001: // Subtraction
               ALU_Out <= A - B;
            5'b00010: // Multiplication
               ALU_Out <= A * B;
            5'b00011: // Division
               if (B != 0) begin
                   ALU_Out <= A / B;
               end else begin
                  `ifdef DEBUG
                     $display("Error: Division by zero at time %t", $time);
                  `endif
                  ALU_Out <= 32'hFFFFFFFF; // Default error value
               end
            5'b00100: // Logical shift left
               ALU_Out <= A << B;
            5'b00101: // Logical shift right
               ALU_Out <= A >> B;
            5'b00110: // Rotate left
               ALU_Out <= {A[30:0], A[31]};
            5'b00111: // Rotate right
               ALU_Out <= {A[0], A[31:1]};
            5'b01000: // Logical and 
               ALU_Out <= A & B;
            5'b01001: // Logical or
               ALU_Out <= A | B;
            5'b01010: // Logical xor 
               ALU_Out <= A ^ B;
            5'b01011: // Logical nor
               ALU_Out <= ~(A | B);
            5'b01100: // Logical nand 
               ALU_Out <= ~(A & B);
            5'b01101: // SLTU
               ALU_Out <= (A < B) ? 1 : 0;
            5'b01110: // Set on less than
                begin // SLT
                    if (A[31] != B[31]) begin
                        ALU_Out <= (A[31] > B[31]) ? 1 : 0;
                    end else begin
                        ALU_Out <= (A < B) ? 1 : 0;
                    end
                end
            5'b01111: // SRA shift right arithmetic   
                begin
                     y = A;
				         for (i = B; i > 0; i = i - 1) 
                     begin
					         y = {y[31],y[31:1]};
				         end
				         ALU_Out = y;
               end
            5'b10000: // Take lower byte sign extended
                begin
                   if (A[7] == 1) begin
                      ALU_Out <= {24'b111111111111111111111111, A[7:0]};
                   end else begin
                      ALU_Out <= {24'b0, A[7:0]};
                   end
                end
            5'b10001: // Take lower half word sign extended
                begin
                   if (A[15] == 1) begin
                      ALU_Out <= {16'b1111111111111111, A[15:0]};
                   end else begin
                      ALU_Out <= {16'b0, A[15:0]};
                   end
                end
            5'b10010: // Take lower byte unsigned
                begin
                   ALU_Out <= {24'b0, A[7:0]};
                end
            5'b10011: // Take lower half word unsigned
                begin
                   ALU_Out <= {16'b0, A[15:0]};
                end  
            default: ALU_Out <= A + B; 
        endcase

        Zero <= (ALU_Out == 0) ? 1 : 0;
        ALUcomplete <= 1; // Indicates operation completion
    end

endmodule

RISC-V_PE/ALU_TB.v
// ALU testbench

// Test bench for instruction decoder

`include "ALU.v"

`timescale 1ns / 1ps

module tb_alu;

    // Parameters
    reg        clk;
    reg [31:0] A;
    reg [31:0] B;
    reg [4:0] ALU_Sel;
    wire [31:0] ALU_Out;
    wire Zero;
    wire ALUcomplete;

    initial $dumpfile("alutestbench.vcd");
    initial $dumpvars(0, tb_alu);

    // Instantiate the ALU module
    alu uut (
        .clk(clk),
        .A(A),
        .B(B),
        .ALU_Sel(ALU_Sel),
        .ALU_Out(ALU_Out),
        .Zero(Zero),
        .ALUcomplete(ALUcomplete)
    );

    // Clock generation
    initial begin
        clk = 0;
        forever #5 clk = ~clk; // Toggle clock every 5 time units
    end

    // Test procedure
    initial begin
        // Monitor outputs
        $monitor("Time: %0dns | A: %h | B: %h | ALU_Sel: %b | ALU_Out: %b | Zero: %b | Complete: %b", 
                 $time, A, B, ALU_Sel, ALU_Out, Zero, ALUcomplete);

        // Test case 1: Addition
        A = 32'h00000005; 
        B = 32'h00000003; 
        ALU_Sel = 5'b00000; // Addition
        #10;

        // Test case 2: Subtraction
        A = 32'h00000005; 
        B = 32'h00000003; 
        ALU_Sel = 5'b00001; // Subtraction
        #10;

        // Test case 3: Multiplication
        A = 32'h00000002; 
        B = 32'h00000003; 
        ALU_Sel = 5'b00010; // Multiplication
        #10;

        // Test case 4: Division
        A = 32'h00000006; 
        B = 32'h00000002; 
        ALU_Sel = 5'b00011; // Division
        #10;

        // Test case 5: Logical Shift Left
        A = 32'h00000001; 
        B = 32'h00000000; 
        ALU_Sel = 5'b00100; // Shift left
        #10;

        // Test case 6: Logical Shift Right
        A = 32'h00000002; 
        B = 32'h00000000; 
        ALU_Sel = 5'b00101; // Shift right
        #10;

        // Test case 7: Rotate Left
        A = 32'h80000000; 
        B = 32'h00000000; 
        ALU_Sel = 5'b00110; // Rotate left
        #10;

        // Test case 8: Rotate Right
        A = 32'h80000000; 
        B = 32'h00000000; 
        ALU_Sel = 5'b00111; // Rotate right
        #10;

        // Test case 9: Logical AND
        A = 32'hF0F0F0F0;
        B = 32'h0F0F0F0F;
        ALU_Sel = 5'b01000; // AND operation
        #10;

        // Test case 10: Logical OR
        A = 32'hF0F0F0F0;
        B = 32'h0F0F0F0F;
        ALU_Sel = 5'b01001; // OR operation
        #10;

         // Test case 11: Logical XOR
         A = 32'hF0F0F0F0;
         B = 32'h0F0F0F0F;
         ALU_Sel = 5'b01010; // XOR operation
         #10;

         // Test case 12: Logical NOR
         A = 32'hF0F0F0F0;
         B = 32'h0F0F0F0F;
         ALU_Sel = 5'b01011; // NOR operation
         #10;

         // Test case 13: Logical NAND
         A = 32'hF0F0F0F0;
         B = 32'h0F0F0F0F;
         ALU_Sel = 5'b01100; // NAND operation
         #10;

         // Test case 14: Set on Less Than Unsigned (SLTU)
         A = 32'd5;
         B = 32'd10;
         ALU_Sel = 5'b01101; // SLTU operation
         #10;

         // Test case 15: Set on Less Than (Signed)
         A = -5;
         B = -10;
         ALU_Sel = 5'b01110; // SLT operation
         #10;

         // Test case for SRA (Shift Right Arithmetic)
         A = 32'b11111111000000000000000000100101;
         B = 4;
         ALU_Sel = 5'b01111; // SRA operation
         #10;

         // Test case for take byte sign extended
         A = 32'b10111111001111011101011010110101;
         B = 32'b0;
         ALU_Sel = 5'b10000; // byte sign extended
         #10;

         // Test case for take half word sign extended
         A = 32'b10111111001111011101011010110101;
         B = 32'b0;
         ALU_Sel = 5'b10001; // half word sign extended
         #10;

         // Test case for take byte unsigned
         A = 32'b10111111001111011101011010110101;
         B = 32'b0;
         ALU_Sel = 5'b10010; // byte unsigned
         #10;

         // Test case for take half word unsigned
         A = 32'b10111111001111011101011010110101;
         B = 32'b0;
         ALU_Sel = 5'b10011; // byte unsigned
         #10;

         $finish;
    end

endmodule

RISC-V_PE/alutestbench.vcd
$date
	Tue Mar 11 22:44:50 2025
$end
$version
	Icarus Verilog
$end
$timescale
	1ps
$end
$scope module tb_alu $end
$var wire 1 ! Zero $end
$var wire 1 " ALUcomplete $end
$var wire 32 # ALU_Out [31:0] $end
$var reg 32 $ A [31:0] $end
$var reg 5 % ALU_Sel [4:0] $end
$var reg 32 & B [31:0] $end
$var reg 1 ' clk $end
$scope module uut $end
$var wire 32 ( A [31:0] $end
$var wire 5 ) ALU_Sel [4:0] $end
$var wire 32 * B [31:0] $end
$var wire 1 ' clk $end
$var reg 32 + ALU_Out [31:0] $end
$var reg 1 " ALUcomplete $end
$var reg 1 ! Zero $end
$var reg 32 , y [31:0] $end
$var integer 32 - i [31:0] $end
$upscope $end
$upscope $end
$enddefinitions $end
$comment Show the parameter values. $end
$dumpall
$end
#0
$dumpvars
bx -
bx ,
bx +
b11 *
b0 )
b101 (
0'
b11 &
b0 %
b101 $
bx #
x"
x!
$end
#5000
b1000 #
b1000 +
1"
1'
#10000
0'
b1 %
b1 )
#15000
0!
b10 #
b10 +
1"
1'
#20000
0'
b10 %
b10 )
b10 $
b10 (
#25000
b110 #
b110 +
1"
1'
#30000
0'
b11 %
b11 )
b10 &
b10 *
b110 $
b110 (
#35000
b11 #
b11 +
1"
1'
#40000
0'
b100 %
b100 )
b0 &
b0 *
b1 $
b1 (
#45000
b1 #
b1 +
1"
1'
#50000
0'
b101 %
b101 )
b10 $
b10 (
#55000
b10 #
b10 +
1"
1'
#60000
0'
b110 %
b110 )
b10000000000000000000000000000000 $
b10000000000000000000000000000000 (
#65000
b1 #
b1 +
1"
1'
#70000
0'
b111 %
b111 )
#75000
b1000000000000000000000000000000 #
b1000000000000000000000000000000 +
1"
1'
#80000
0'
b1000 %
b1000 )
b1111000011110000111100001111 &
b1111000011110000111100001111 *
b11110000111100001111000011110000 $
b11110000111100001111000011110000 (
#85000
b0 #
b0 +
1"
1'
#90000
0'
b1001 %
b1001 )
#95000
1!
b11111111111111111111111111111111 #
b11111111111111111111111111111111 +
1"
1'
#100000
0'
b1010 %
b1010 )
#105000
0!
1"
1'
#110000
0'
b1011 %
b1011 )
#115000
b0 #
b0 +
1"
1'
#120000
0'
b1100 %
b1100 )
#125000
1!
b11111111111111111111111111111111 #
b11111111111111111111111111111111 +
1"
1'
#130000
0'
b1101 %
b1101 )
b1010 &
b1010 *
b101 $
b101 (
#135000
0!
b1 #
b1 +
1"
1'
#140000
0'
b1110 %
b1110 )
b11111111111111111111111111110110 &
b11111111111111111111111111110110 *
b11111111111111111111111111111011 $
b11111111111111111111111111111011 (
#145000
b0 #
b0 +
1"
1'
#150000
0'
b1111 %
b1111 )
b100 &
b100 *
b11111111000000000000000000100101 $
b11111111000000000000000000100101 (
#155000
1"
b11111111111100000000000000000010 #
b11111111111100000000000000000010 +
b0 -
b11111111111100000000000000000010 ,
1'
#160000
0'
b10000 %
b10000 )
b0 &
b0 *
b10111111001111011101011010110101 $
b10111111001111011101011010110101 (
#165000
b11111111111111111111111110110101 #
b11111111111111111111111110110101 +
1"
1'
#170000
0'
b10001 %
b10001 )
#175000
b11111111111111111101011010110101 #
b11111111111111111101011010110101 +
1"
1'
#180000
0'
b10010 %
b10010 )
#185000
b10110101 #
b10110101 +
1"
1'
#190000
0'
b10011 %
b10011 )
#195000
b1101011010110101 #
b1101011010110101 +
1"
1'
