RISC-V_PE/decoder.v
// Instruction decoder module

`define DEBUG

module decoder (op, funct3, funct7, rs1, rs2, rd, imm12, immhi, instruction, decodeComplete);

input  [31:0] instruction;
output reg [6:0]  op;
output reg [2:0]  funct3;
output reg [6:0]  funct7;
output reg [4:0]  rs1; //index for register 1 or opperand 1
output reg [4:0]  rs2; //index for register 2 or opperand 2
output reg [4:0]  rd;  //index for the destination register
output reg [11:0] imm12; //immidiate value for I type, S type and B type instructions
output reg [19:0] immhi; //immidiate value for U and J type instructions
output reg        decodeComplete;



always @(*) begin
    // Extract opcode
    op <= instruction [6:0];

    //Default values for outputs
    funct3 <= 3'b000;
    funct7 <= 7'b0000000;
    rs1 <= 5'b00000;
    rs2 <= 5'b00000;
    rd <= 5'b00000;
    imm12 <= 12'b000000000000;
    immhi <= 20'b00000000000000000000;
    decodeComplete <= 0;
    

    case (op)
        7'b0110011 , 7'b1010011: // Type R instruction
            begin
                funct3 <= instruction[14:12];
                funct7 <= instruction[31:25];
                rs1 <= instruction[19:15];
                rs2 <= instruction[24:20];
                rd <= instruction[11:7];
            end

        7'b1101111: // Type J instruction
            begin
                rd <= instruction[11:7];
                immhi <= instruction[31:12];
            end

        7'b0010111 , 7'b0110111: //Type U instruction
            begin
                rd <= instruction[11:7];
                immhi <= instruction[31:12];
            end

        7'b0100011 , 7'b0100111: //Type S instruction
            begin
                funct3 <= instruction[14:12];
                imm12 <= {instruction[31:25], instruction[11:7]};
                rs1 <= instruction[19:15];
                rs2 <= instruction[24:20];
            end

        7'b1100011: //Type B instruction
            begin
                funct3 <= instruction[14:12];
                rs1 <= instruction[19:15];
                rs2 <= instruction[24:20];
                imm12 <= {instruction[31], instruction[7], instruction[30:25], instruction[11:8], 1'b0};
            end

        7'b0000011 , 7'b0010011 , 7'b1100111 , 7'b0000111: //Type I instruction
            begin
                funct3 <= instruction[14:12];
                rs1 <= instruction[19:15];
                rd <= instruction[11:7];
                imm12 <= instruction[31:20];
            end

        default: 
            begin
                `ifdef DEBUG
                     $display("This code does not correspond to any valid operation");
                `endif
                //op <= 7'b1111111; // Invalid opcode indicator
            end
    endcase

    decodeComplete <= (op == 7'b0110011 || op == 7'b1010011 || op == 7'b1101111 || op == 7'b0010111 || op == 7'b0100011 || op == 7'b1100011 || op == 7'b0100111 || op == 7'b0000011 || op == 7'b0010011 || op == 7'b1100111 || op == 7'b0000111 || op == 7'b1100011);
    

    end

    endmodule

RISC-V_PE/decoTB.v
// Test bench for instruction decoder


`timescale 1ns / 1ps
`include "decoder.v"

module tb_decoder;

    // Parameters
    reg [31:0] instruction;
    wire [6:0]  op;
    wire [2:0]  funct3;
    wire [6:0]  funct7;
    wire [4:0]  rs1; 
    wire [4:0]  rs2; 
    wire [4:0]  rd;  
    wire [11:0] imm12; 
    wire [19:0] immhi;
    wire decodeComplete;

    initial $dumpfile("decodertestbench.vcd");
    initial $dumpvars(0, tb_decoder);

    // Instantiate the decoder module
    decoder uut (
        .instruction(instruction),
        .op(op),
        .funct3(funct3),
        .funct7(funct7),
        .rs1(rs1),
        .rs2(rs2),
        .rd(rd),
        .imm12(imm12),
        .immhi(immhi),
        .decodeComplete(decodeComplete)
    );

    // Test procedure
    initial begin
        instruction = 32'b0;

        // Monitor outputs
        $monitor("Time: %0dns | Instruction: %h | op: %d | funct3: %b | funct7: %b | rs1: %b | rs2: %b | rd: %b | imm12: %b | immhi: %b | decodeComplete: %b", 
                 $time, instruction, op, funct3, funct7, rs1, rs2, rd, imm12, immhi, decodeComplete);

        // Test case 1: Case R instruction
        instruction = 32'b0000000_00010_00011_100_00001_0110011; //XOR
        #10;
        instruction = 32'b0;

        // Test case 2: Case J instruction
        instruction = 32'b00000000000010000011_00001_1101111; // Jump
        #10;
        instruction = 32'b0;

        // Test case 3: Case S instruction
        instruction = 32'b0000001_00010_00011_001_00001_0100011; // Store half
        #10;
        instruction = 32'b0;

        // Test case 4: Case B type
        instruction = 32'b0001000_00010_00011_100_00001_1100011; // Branch if less than
        #10;
        instruction = 32'b0;

        // Test case 5: Case I type with op 103
        instruction = 32'b000000001000_00011_000_00001_1100111; // Jump and link register
        #10;
        instruction = 32'b0;

        // Test case 5: Case I type with op 3
        instruction = 32'b000000100011_01010_000_10101_0000011; // Load byte signed
        #10;
        instruction = 32'b0;

        // Test case 5: Case I type with op 19
        instruction = 32'b000000001000_00011_010_00001_0010011; // Set less than immidiate
        #10;
        instruction = 32'b0;

        // Test case 5: Case U type with op 23
        instruction = 32'b00000000100000011010_00001_0010111; // Add upper imm to PC
        #10;
        instruction = 32'b0;

        // Test case 5: Case U type with op 55
        instruction = 32'b00000000100000011010_00001_0110111; // load upper immidiate
        #10;
        instruction = 32'b0;

         $finish;
    end

endmodule

RISC-V_PE/decodertestbench.vcd
$date
	Tue Mar 11 08:59:08 2025
$end
$version
	Icarus Verilog
$end
$timescale
	1ps
$end
$scope module tb_decoder $end
$var wire 5 ! rs2 [4:0] $end
$var wire 5 " rs1 [4:0] $end
$var wire 5 # rd [4:0] $end
$var wire 7 $ op [6:0] $end
$var wire 20 % immhi [19:0] $end
$var wire 12 & imm12 [11:0] $end
$var wire 7 ' funct7 [6:0] $end
$var wire 3 ( funct3 [2:0] $end
$var wire 1 ) decodeComplete $end
$var reg 32 * instruction [31:0] $end
$scope module uut $end
$var wire 32 + instruction [31:0] $end
$var reg 1 ) decodeComplete $end
$var reg 3 , funct3 [2:0] $end
$var reg 7 - funct7 [6:0] $end
$var reg 12 . imm12 [11:0] $end
$var reg 20 / immhi [19:0] $end
$var reg 7 0 op [6:0] $end
$var reg 5 1 rd [4:0] $end
$var reg 5 2 rs1 [4:0] $end
$var reg 5 3 rs2 [4:0] $end
$upscope $end
$upscope $end
$enddefinitions $end
$comment Show the parameter values. $end
$dumpall
$end
#0
$dumpvars
b10 3
b11 2
b1 1
b110011 0
b0 /
b0 .
b0 -
b100 ,
b1000011100000010110011 +
b1000011100000010110011 *
1)
b100 (
b0 '
b0 &
b0 %
b110011 $
b1 #
b11 "
b10 !
$end
#10000
b10000011 %
b10000011 /
1)
b1 #
b1 1
b0 !
b0 3
b0 "
b0 2
b0 (
b0 ,
b1101111 $
b1101111 0
b10000011000011101111 *
b10000011000011101111 +
#20000
b10 !
b10 3
b11 "
b11 2
b100001 &
b100001 .
b1 (
b1 ,
1)
b0 %
b0 /
b0 #
b0 1
b100011 $
b100011 0
b10001000011001000010100011 *
b10001000011001000010100011 +
#30000
1)
b100100000000 &
b100100000000 .
b10 !
b10 3
b11 "
b11 2
b100 (
b100 ,
b1100011 $
b1100011 0
b10000001000011100000011100011 *
b10000001000011100000011100011 +
#40000
b1 #
b1 1
1)
b1000 &
b1000 .
b0 !
b0 3
b11 "
b11 2
b0 (
b0 ,
b1100111 $
b1100111 0
b100000011000000011100111 *
b100000011000000011100111 +
#50000
1)
b100011 &
b100011 .
b10101 #
b10101 1
b1010 "
b1010 2
b11 $
b11 0
b10001101010000101010000011 *
b10001101010000101010000011 +
#60000
b10 (
b10 ,
1)
b1000 &
b1000 .
b1 #
b1 1
b11 "
b11 2
b10011 $
b10011 0
b100000011010000010010011 *
b100000011010000010010011 +
#70000
b100000011010 %
b100000011010 /
1)
b0 &
b0 .
b1 #
b1 1
b0 "
b0 2
b0 (
b0 ,
b10111 $
b10111 0
b100000011010000010010111 *
b100000011010000010010111 +
#80000
0)
b100000011010 %
b100000011010 /
b1 #
b1 1
b110111 $
b110111 0
b100000011010000010110111 *
b100000011010000010110111 +
#90000
b0 %
b0 /
b0 #
b0 1
b0 $
b0 0
b0 *
b0 +
