RISC-V_PE/mux3_1.v
module mux3_1 (
    input      [31:0] in_1,
    input      [31:0] in_2,
    input      [31:0] in_3,
    input      [1:0]  sel,
    output reg [31:0] data_out
);
    output reg [31:0] data_out = 32'b0;
    always @(*) begin
        case(sel)
            2'b00: data_out = in_1; // Select in_1
            2'b01: data_out = in_2; // Select in_2
            2'b10: data_out = in_3; // Select in_3
            default: data_out = 32'b0; // Default case (optional)
        endcase
    end

endmodule

RISC-V_PE/reg.v
//Modelo del registro de 32 bits para registro de instrucciones y registros de entrada

module Register (
    input             clock,
    input             r_enable,
    input      [31:0] data_in,
    input             reset, // Add reset signal
    output reg [31:0] data_out
);
    

    always @(posedge clock or posedge reset) begin
        if (reset) begin
            data_out <= 32'b0; // Reset the output to 0
        end else if (r_enable) begin
            data_out <= data_in; // Load data on enable
            $display("data_out: %b", data_out);
        end
    end

endmodule

RISC-V_PE/MUX_Reg.v
`include "mux3_1.v"
`include "reg.v"

//Module combining mux and registers

module MUX_Reg (
    input clk,
    input [31:0] inRs1,
    input [31:0] inBusA,
    input [31:0] inPC,
    input [31:0] inRs2,
    input [31:0] inBusB,
    input [31:0] inImm,
    input        Aenable,
    input        Benable,
    input        reset,
    input [1:0]  Asel,
    input [1:0]  Bsel,
    output [31:0] Aout,
    output [31:0] Bout
);

    //Internal signals
    wire [31:0] Asignal;
    wire [31:0] Bsignal;

    Register regA (
        .clock(clk),
        .reset(reset),
        .r_enable(Aenable), 
        .data_in(Asignal), 
        .data_out(Aout) 
    );

    Register regB (
        .clock(clk),
        .reset(reset),
        .r_enable(Benable), 
        .data_in(Bsignal), 
        .data_out(Bout)
    );

    mux3_1 muxA (
        .in_1(inRs1),
        .in_2(inBusA),
        .in_3(inPC),
        .sel(Asel),
        .data_out(Asignal)
    );

    mux3_1 muxB (
        .in_1(inRs2),
        .in_2(inBusB),
        .in_3(inImm),
        .sel(Bsel),
        .data_out(Bsignal)
    );

    endmodule

RISC-V_PE/MUXRegTB.v
// Test bench for the register module

`include "MUX_Reg.v"
`timescale 1ns / 1ps

module tb_MUXReg;

    // Parameters
    reg clk;
    reg [31:0] inRs1;
    reg [31:0] inBusA;
    reg [31:0] inPC;
    reg [31:0] inRs2;
    reg [31:0] inBusB;
    reg [31:0] inImm;
    reg        Aenable;
    reg        Benable;
    reg        reset;
    reg [1:0]  Asel;
    reg [1:0]  Bsel;
    wire [31:0] Aout;
    wire [31:0] Bout;

    initial $dumpfile("muxRegTestbench.vcd");
    initial $dumpvars(0, tb_MUXReg);

    // Instantiate the Register module
    MUX_Reg uut (
        .clk(clk),
        .inRs1(inRs1),
        .inBusA(inBusA),
        .inPC(inPC),
        .inRs2(inRs2),
        .inBusB(inBusB),
        .inImm(inImm),
        .Aenable(Aenable),
        .Benable(Benable),
        .reset(reset),
        .Asel(Asel),
        .Bsel(Bsel),
        .Aout(Aout),
        .Bout(Bout)
    );

    // Clock generation
    initial begin
        clk = 0;
        forever #5 clk = ~clk; // Toggle clock every 5 time units
    end

    // Test procedure
    initial begin
        // Monitor outputs
        $monitor("Time: %0dns | reset: %b | Aout: %d | Bout: %d | Aenable: %b | Benable: %b", 
                 $time, reset, Aout, Bout, Aenable, Benable);

        // Initialize signals
        reset = 1; // Assert reset
        Aenable = 0;
        Benable = 0; 
        inRs1 = 0; 
        inRs2 = 0;
        inBusA = 0;
        inBusB = 0;
        inPC = 0;
        inImm = 0;
        #10;

        reset = 0; // Deassert reset
        #10;

        Asel = 2'b00; //Select rs1
        Bsel = 2'b00; //Select rs2
        inRs1 = 35;
        inRs2 = 84;
        inBusA = 22;
        inBusB = 67;
        inPC = 52;
        inImm = 12;
        #10


        // Test case 1: Enable register and load data
        Aenable = 1; 
        Benable = 1;
        #10;

        // Check output after loading data
        Aenable = 0; // Disable register loading
        Benable = 0;
        #10;

        // Test case 2: Load new data while enabled
        Aenable = 1; 
        Benable = 1;
        Asel = 2'b01; // Select data from bus
        Bsel = 2'b01; 
        #10;

        // Check output after loading new data
        Aenable = 0; // Disable register loading
        Benable = 0;
        #10;

        // Test case 3: Assert reset again
        reset = 1; 
        #10;

        // Check output after reset (should be zero)
        reset = 0; 
        #10;

        // Final state check with no enable and some input data
        Aenable = 0; 
        Benable = 0;
        Asel = 2'b10; //Select PC
        Bsel = 2'b10; //Select imm value 
        #10;

        //Enable values to see PC and imm value
        Aenable = 1;
        Benable = 1;
        #10

        #10
         $finish;
    end

endmodule

RISC-V_PE/muxRegTestbench.vcd
$date
	Tue Mar 11 16:05:53 2025
$end
$version
	Icarus Verilog
$end
$timescale
	1ps
$end
$scope module tb_MUXReg $end
$var wire 32 ! Bout [31:0] $end
$var wire 32 " Aout [31:0] $end
$var reg 1 # Aenable $end
$var reg 2 $ Asel [1:0] $end
$var reg 1 % Benable $end
$var reg 2 & Bsel [1:0] $end
$var reg 1 ' clk $end
$var reg 32 ( inBusA [31:0] $end
$var reg 32 ) inBusB [31:0] $end
$var reg 32 * inImm [31:0] $end
$var reg 32 + inPC [31:0] $end
$var reg 32 , inRs1 [31:0] $end
$var reg 32 - inRs2 [31:0] $end
$var reg 1 . reset $end
$scope module uut $end
$var wire 1 # Aenable $end
$var wire 2 / Asel [1:0] $end
$var wire 1 % Benable $end
$var wire 2 0 Bsel [1:0] $end
$var wire 1 ' clk $end
$var wire 32 1 inBusA [31:0] $end
$var wire 32 2 inBusB [31:0] $end
$var wire 32 3 inImm [31:0] $end
$var wire 32 4 inPC [31:0] $end
$var wire 32 5 inRs1 [31:0] $end
$var wire 32 6 inRs2 [31:0] $end
$var wire 1 . reset $end
$var wire 32 7 Bsignal [31:0] $end
$var wire 32 8 Bout [31:0] $end
$var wire 32 9 Asignal [31:0] $end
$var wire 32 : Aout [31:0] $end
$scope module muxA $end
$var wire 32 ; in_1 [31:0] $end
$var wire 32 < in_2 [31:0] $end
$var wire 32 = in_3 [31:0] $end
$var wire 2 > sel [1:0] $end
$var reg 32 ? data_out [31:0] $end
$upscope $end
$scope module muxB $end
$var wire 32 @ in_1 [31:0] $end
$var wire 32 A in_2 [31:0] $end
$var wire 32 B in_3 [31:0] $end
$var wire 2 C sel [1:0] $end
$var reg 32 D data_out [31:0] $end
$upscope $end
$scope module regA $end
$var wire 1 ' clock $end
$var wire 32 E data_in [31:0] $end
$var wire 1 # r_enable $end
$var wire 1 . reset $end
$var reg 32 F data_out [31:0] $end
$upscope $end
$scope module regB $end
$var wire 1 ' clock $end
$var wire 32 G data_in [31:0] $end
$var wire 1 % r_enable $end
$var wire 1 . reset $end
$var reg 32 H data_out [31:0] $end
$upscope $end
$upscope $end
$upscope $end
$enddefinitions $end
$comment Show the parameter values. $end
$dumpall
$end
#0
$dumpvars
b0 H
b0 G
b0 F
b0 E
b0 D
bx C
b0 B
b0 A
b0 @
b0 ?
bx >
b0 =
b0 <
b0 ;
b0 :
b0 9
b0 8
b0 7
b0 6
b0 5
b0 4
b0 3
b0 2
b0 1
bx 0
bx /
1.
b0 -
b0 ,
b0 +
b0 *
b0 )
b0 (
0'
bx &
0%
bx $
0#
b0 "
b0 !
$end
#5000
1'
#10000
0'
0.
#15000
1'
#20000
b1010100 7
b1010100 D
b1010100 G
b100011 9
b100011 ?
b100011 E
0'
b1100 *
b1100 3
b1100 B
b110100 +
b110100 4
b110100 =
b1000011 )
b1000011 2
b1000011 A
b10110 (
b10110 1
b10110 <
b1010100 -
b1010100 6
b1010100 @
b100011 ,
b100011 5
b100011 ;
b0 &
b0 0
b0 C
b0 $
b0 /
b0 >
#25000
1'
#30000
0'
1%
1#
#35000
b100011 "
b100011 :
b100011 F
b1010100 !
b1010100 8
b1010100 H
1'
#40000
0'
0%
0#
#45000
1'
#50000
b1000011 7
b1000011 D
b1000011 G
b10110 9
b10110 ?
b10110 E
0'
b1 &
b1 0
b1 C
b1 $
b1 /
b1 >
1%
1#
#55000
b10110 "
b10110 :
b10110 F
b1000011 !
b1000011 8
b1000011 H
1'
#60000
0'
0%
0#
#65000
1'
#70000
b0 "
b0 :
b0 F
b0 !
b0 8
b0 H
0'
1.
#75000
1'
#80000
0'
0.
#85000
1'
#90000
b1100 7
b1100 D
b1100 G
b110100 9
b110100 ?
b110100 E
0'
b10 &
b10 0
b10 C
b10 $
b10 /
b10 >
#95000
1'
#100000
0'
1%
1#
#105000
b110100 "
b110100 :
b110100 F
b1100 !
b1100 8
b1100 H
1'
