RISC-V_PE/BusInterface.v
module bus_interface (
    input clk,
    input reset,
    //Inputs from PE
    input [31:0] mem_addressPE,  //mem_Address from PE for global memory
    input [31:0] result_inPE,    //result_out from PE
    input [31:0] PCoutPE,        //new program counter to be sent to the controller
    input [4:0] rs1OutPE,        //Select data from PE to be sent to local memory
    input [4:0] rs2OutPE,        //Select data from PE to be sent to local memory
    input [4:0] rdOutPE,         //Select data from PE to be sent to local memory
    input       reg_selectPE,    //Select signal for local memory (read 1 or 2 data)
    input       mem_readPE,      //Signal to read from global memory
    input       mem_writePE,     //Signal to write to global memory
    input       rd_writePE,      //Signal to write to local memory
    input       read_enPE,       //Signal to read from local memory

    //Outputs to the PE
    output reg [31:0] PCinPE,    //Program counter being sent to the PE
    output reg [31:0] instructionPE, //Instruction loaded into PE
    output reg [31:0] AmuxPE,    //Data being sent to A mux
    output reg [31:0] BmuxPE,    //Data being sent to B mux
    output reg        mem_ackPE, //Memory acknowledgment signal into the PE
    output reg        data_ReadyPE, //data_Ready signal into the PE

    //Signals to/from the bus
    output reg bus_request,    //Request signal sent to the arbiter
    input      grant,      //Grant signal from the arbiter
    output reg [31:0] mem_addressBus,  //mem_Address sent to bus for global memory
    output reg [31:0] result_outBus,   //result_out sent to bus
    output reg [31:0] PCoutBus,        //new program counter to be sent to the controller
    output reg [4:0] rs1OutBus,        //Select data from PE to be sent to local memory
    output reg [4:0] rs2OutBus,        //Select data from PE to be sent to local memory
    output reg [4:0] rdOutBus,         //Select data from PE to be sent to local memory
    output reg       reg_selectBus,    //Select signal for local memory (read 1 or 2 data)
    output reg       mem_readBus,      //Signal to read from global memory
    output reg       mem_writeBus,     //Signal to write to global memory
    output reg       rd_writeBus,      //Signal to write to local memory
    output reg       read_enBus,
    input [31:0] PCinBus,    //Program counter being sent to the PE
    input [31:0] instructionBus, //Instruction loaded into PE
    input [31:0] AmuxBus,    //Data being sent to A mux
    input [31:0] BmuxBus,    //Data being sent to B mux
    input        mem_ackBus, //Memory acknowledgment signal coming from the global memory
    input        data_ReadyBus, //register read complete
    input [31:0] memData,      //Data coming from global memory
    input        instrWrite    //Signal from controller to write instruction into PE
);

    reg active; // Keep track of the bus request state

    always @(posedge clk or posedge reset) begin
        if (reset) begin
            bus_request <= 0;
            PCinPE <= 0;
            instructionPE <= 0;
            AmuxPE <= 0;
            BmuxPE <= 0;
            mem_ackPE <= 0;
            data_ReadyPE <= 0;
            mem_addressBus <= 0;
            result_outBus <= 0;
            PCoutBus <= 0;
            rs1OutBus <= 0;
            rs2OutBus <= 0;
            rdOutBus <= 0;
            reg_selectBus <= 0;
            mem_readBus <= 0;
            mem_writeBus <= 0;
            rd_writeBus <= 0;
            read_enBus <= 0;
            active <= 0;
        end else begin
            if ((mem_readPE || mem_writePE || rd_writePE || read_enPE || instrWrite) && !active) begin
                bus_request <= 1; // Request the bus
            end
            if (grant) begin
                PCoutBus <= PCoutPE;
                if (mem_writePE)
                begin
                    mem_addressBus <= mem_addressPE;
                    mem_writeBus <= mem_writePE;
                    result_outBus <= result_inPE;
                end
                if (mem_readPE)
                begin
                    mem_addressBus <= result_inPE; //Address is calculated from ALU
                    mem_readBus <= mem_readPE;
                end
                if (rd_writePE)
                begin 
                    rdOutBus <= rdOutPE; //Forward select for local memory write
                    rd_writeBus <= rd_writePE;
                    result_outBus <= result_inPE; //Result from ALU to be written in rd
                end
                if (read_enPE)
                begin
                    rs1OutBus <= rs1OutPE;
                    rs2OutBus <= rs2OutPE;
                    read_enBus <= read_enPE;
                    reg_selectBus <= reg_selectPE;
                end
                bus_request <= 0; // Clear the request once granted
                active <= 1;
            end
            if (active) begin
                PCinPE <= PCinBus;
                if (instrWrite)
                begin
                    instructionPE <= instructionBus;
                end
                if (mem_ackBus)
                begin
                    AmuxPE <= memData;
                    mem_ackPE <= mem_ackBus;
                end
                if (data_ReadyBus)
                begin
                    AmuxPE <= AmuxBus;
                    BmuxPE <= BmuxBus;
                    data_ReadyPE <= data_ReadyBus;
                end
                active <= 0;
                bus_request <= 0;

            end
        end
    end
endmodule

RISC-V_PE/BusInterfaceTB.v
`include "BusInterface.v"
`timescale 1ns / 1ps

module tb_bus_interface;

    // Testbench signals
    reg clk;
    reg reset;

    // Inputs from the PE
    reg [31:0] mem_addressPE;
    reg [31:0] result_inPE;
    reg [31:0] PCoutPE;
    reg [4:0] rs1OutPE;
    reg [4:0] rs2OutPE;
    reg [4:0] rdOutPE;
    reg reg_selectPE;
    reg mem_readPE;
    reg mem_writePE;
    reg rd_writePE;
    reg read_enPE;

    // Outputs to the PE
    wire [31:0] PCinPE;
    wire [31:0] instructionPE;
    wire [31:0] AmuxPE;
    wire [31:0] BmuxPE;
    wire mem_ackPE;
    wire data_ReadyPE;

    // Signals to/from the bus
    wire bus_request;
    reg grant;
    wire [31:0] mem_addressBus;
    wire [31:0] result_outBus;
    wire [31:0] PCoutBus;
    wire [4:0] rs1OutBus;
    wire [4:0] rs2OutBus;
    wire [4:0] rdOutBus;
    wire reg_selectBus;
    wire mem_readBus;
    wire mem_writeBus;
    wire rd_writeBus;
    wire read_enBus;
    reg [31:0] PCinBus;
    reg [31:0] instructionBus;
    reg [31:0] AmuxBus;
    reg [31:0] BmuxBus;
    reg mem_ackBus;
    reg data_ReadyBus;
    reg [31:0] memData;
    reg instrWrite;

    // Instantiate the bus_interface module
    bus_interface uut (
        .clk(clk),
        .reset(reset),
        .mem_addressPE(mem_addressPE),
        .result_inPE(result_inPE),
        .PCoutPE(PCoutPE),
        .rs1OutPE(rs1OutPE),
        .rs2OutPE(rs2OutPE),
        .rdOutPE(rdOutPE),
        .reg_selectPE(reg_selectPE),
        .mem_readPE(mem_readPE),
        .mem_writePE(mem_writePE),
        .rd_writePE(rd_writePE),
        .read_enPE(read_enPE),
        .PCinPE(PCinPE),
        .instructionPE(instructionPE),
        .AmuxPE(AmuxPE),
        .BmuxPE(BmuxPE),
        .mem_ackPE(mem_ackPE),
        .data_ReadyPE(data_ReadyPE),
        .bus_request(bus_request),
        .grant(grant),
        .mem_addressBus(mem_addressBus),
        .result_outBus(result_outBus),
        .PCoutBus(PCoutBus),
        .rs1OutBus(rs1OutBus),
        .rs2OutBus(rs2OutBus),
        .rdOutBus(rdOutBus),
        .reg_selectBus(reg_selectBus),
        .mem_readBus(mem_readBus),
        .mem_writeBus(mem_writeBus),
        .rd_writeBus(rd_writeBus),
        .read_enBus(read_enBus),
        .PCinBus(PCinBus),
        .instructionBus(instructionBus),
        .AmuxBus(AmuxBus),
        .BmuxBus(BmuxBus),
        .mem_ackBus(mem_ackBus),
        .data_ReadyBus(data_ReadyBus),
        .memData(memData),
        .instrWrite(instrWrite)
    );

    // Clock generation
    initial begin
        clk = 0;
        forever #5 clk = ~clk; // Clock period = 10 time units
    end

    // Testbench logic
    initial begin
        // Dump waveform for debugging
        $dumpfile("tb_bus_interface.vcd");
        $dumpvars(0, tb_bus_interface);

        $monitor("Time: %0dns | PCout: %d | mem_address: %b | reg_select: %b | mem_read: %b | mem_write: %b | rs1: %b | rs2: %b | rd: %b | rd_Write: %b | result_out: %b | PCinPE: %d | instruction: %h | AmuxPE: %b | BmuxPE: %b | mem_ackPE: %b | data_ReadyPE: %b", 
                 $time, PCoutBus, mem_addressBus, reg_selectBus, mem_readBus, mem_writeBus, rs1OutBus, rs2OutBus, rdOutBus, rd_writeBus, result_outBus, PCinPE, instructionPE, AmuxPE, BmuxPE, mem_ackPE, data_ReadyPE);


        // Initialize signals
        reset = 1;
        grant = 0;
        mem_addressPE = 32'd0;
        result_inPE = 32'd0;
        PCoutPE = 32'd0;
        rs1OutPE = 5'd0;
        rs2OutPE = 5'd0;
        rdOutPE = 5'd0;
        reg_selectPE = 0;
        mem_readPE = 0;
        mem_writePE = 0;
        rd_writePE = 0;
        read_enPE = 0;
        instrWrite = 0;
        mem_ackBus = 0;
        data_ReadyBus = 0;

        #10 reset = 0; // Release reset

        // Test Case 1: PE requests a global memory write
        mem_addressPE = 32'hAABBCCDD;
        result_inPE = 32'h12345678;
        mem_writePE = 1; // Request memory write
        grant = 1; // Bus grants access
        #10 mem_writePE = 0; // Clear memory write signal

        // Test Case 2: PE requests a global memory read
        mem_addressPE = 32'h11223344;
        mem_readPE = 1; // Request memory read
        grant = 1; // Bus grants access
        mem_ackBus = 1; // Memory acknowledgment from bus
        memData = 32'h87654321; // Data provided by global memory
        #10 mem_readPE = 0; // Clear memory read signal
        mem_ackBus = 0;

        // Test Case 3: Instruction write to PE
        instrWrite = 1; // Controller writes instruction into PE
        instructionBus = 32'hDEADBEEF;
        #10 instrWrite = 0;

        // Test Case 4: PE requests to write to local memory
        rdOutPE = 5'd10;
        result_inPE = 32'hFACECAFE;
        rd_writePE = 1; // Request to write to local memory
        grant = 1; // Bus grants access
        #10 rd_writePE = 0;

        // Test Case 5: PE requests to read from local memory
        rs1OutPE = 5'd1;
        rs2OutPE = 5'd2;
        reg_selectPE = 1;
        read_enPE = 1; // Request read enable
        grant = 1;
        AmuxBus = 32'hABCD1234;
        BmuxBus = 32'hDCBA4321;
        data_ReadyBus = 1; // Data ready signal
        #10 read_enPE = 0;
        reg_selectPE = 0;
        data_ReadyBus = 0;

        // End simulation
        #20 $finish;
    end

endmodule

RISC-V_PE/tb_bus_interface.vcd
$date
	Thu Mar 27 21:28:55 2025
$end
$version
	Icarus Verilog
$end
$timescale
	1ps
$end
$scope module tb_bus_interface $end
$var wire 5 ! rs2OutBus [4:0] $end
$var wire 5 " rs1OutBus [4:0] $end
$var wire 32 # result_outBus [31:0] $end
$var wire 1 $ reg_selectBus $end
$var wire 1 % read_enBus $end
$var wire 1 & rd_writeBus $end
$var wire 5 ' rdOutBus [4:0] $end
$var wire 1 ( mem_writeBus $end
$var wire 1 ) mem_readBus $end
$var wire 32 * mem_addressBus [31:0] $end
$var wire 1 + mem_ackPE $end
$var wire 32 , instructionPE [31:0] $end
$var wire 1 - data_ReadyPE $end
$var wire 1 . bus_request $end
$var wire 32 / PCoutBus [31:0] $end
$var wire 32 0 PCinPE [31:0] $end
$var wire 32 1 BmuxPE [31:0] $end
$var wire 32 2 AmuxPE [31:0] $end
$var reg 32 3 AmuxBus [31:0] $end
$var reg 32 4 BmuxBus [31:0] $end
$var reg 32 5 PCinBus [31:0] $end
$var reg 32 6 PCoutPE [31:0] $end
$var reg 1 7 clk $end
$var reg 1 8 data_ReadyBus $end
$var reg 1 9 grant $end
$var reg 1 : instrWrite $end
$var reg 32 ; instructionBus [31:0] $end
$var reg 32 < memData [31:0] $end
$var reg 1 = mem_ackBus $end
$var reg 32 > mem_addressPE [31:0] $end
$var reg 1 ? mem_readPE $end
$var reg 1 @ mem_writePE $end
$var reg 5 A rdOutPE [4:0] $end
$var reg 1 B rd_writePE $end
$var reg 1 C read_enPE $end
$var reg 1 D reg_selectPE $end
$var reg 1 E reset $end
$var reg 32 F result_inPE [31:0] $end
$var reg 5 G rs1OutPE [4:0] $end
$var reg 5 H rs2OutPE [4:0] $end
$scope module uut $end
$var wire 32 I AmuxBus [31:0] $end
$var wire 32 J BmuxBus [31:0] $end
$var wire 32 K PCinBus [31:0] $end
$var wire 32 L PCoutPE [31:0] $end
$var wire 1 7 clk $end
$var wire 1 8 data_ReadyBus $end
$var wire 1 9 grant $end
$var wire 1 : instrWrite $end
$var wire 32 M instructionBus [31:0] $end
$var wire 32 N memData [31:0] $end
$var wire 1 = mem_ackBus $end
$var wire 32 O mem_addressPE [31:0] $end
$var wire 1 ? mem_readPE $end
$var wire 1 @ mem_writePE $end
$var wire 5 P rdOutPE [4:0] $end
$var wire 1 B rd_writePE $end
$var wire 1 C read_enPE $end
$var wire 1 D reg_selectPE $end
$var wire 1 E reset $end
$var wire 32 Q result_inPE [31:0] $end
$var wire 5 R rs1OutPE [4:0] $end
$var wire 5 S rs2OutPE [4:0] $end
$var reg 32 T AmuxPE [31:0] $end
$var reg 32 U BmuxPE [31:0] $end
$var reg 32 V PCinPE [31:0] $end
$var reg 32 W PCoutBus [31:0] $end
$var reg 1 X active $end
$var reg 1 . bus_request $end
$var reg 1 - data_ReadyPE $end
$var reg 32 Y instructionPE [31:0] $end
$var reg 1 + mem_ackPE $end
$var reg 32 Z mem_addressBus [31:0] $end
$var reg 1 ) mem_readBus $end
$var reg 1 ( mem_writeBus $end
$var reg 5 [ rdOutBus [4:0] $end
$var reg 1 & rd_writeBus $end
$var reg 1 % read_enBus $end
$var reg 1 $ reg_selectBus $end
$var reg 32 \ result_outBus [31:0] $end
$var reg 5 ] rs1OutBus [4:0] $end
$var reg 5 ^ rs2OutBus [4:0] $end
$upscope $end
$upscope $end
$enddefinitions $end
$comment Show the parameter values. $end
$dumpall
$end
#0
$dumpvars
b0 ^
b0 ]
b0 \
b0 [
b0 Z
b0 Y
0X
b0 W
b0 V
b0 U
b0 T
b0 S
b0 R
b0 Q
b0 P
b0 O
bx N
bx M
b0 L
bx K
bx J
bx I
b0 H
b0 G
b0 F
1E
0D
0C
0B
b0 A
0@
0?
b0 >
0=
bx <
bx ;
0:
09
08
07
b0 6
bx 5
bx 4
bx 3
b0 2
b0 1
b0 0
b0 /
0.
0-
b0 ,
0+
b0 *
0)
0(
b0 '
0&
0%
0$
b0 #
b0 "
b0 !
$end
#5000
17
#10000
07
19
1@
b10010001101000101011001111000 F
b10010001101000101011001111000 Q
b10101010101110111100110011011101 >
b10101010101110111100110011011101 O
0E
#15000
1X
b10010001101000101011001111000 #
b10010001101000101011001111000 \
1(
b10101010101110111100110011011101 *
b10101010101110111100110011011101 Z
0.
17
#20000
07
b10000111011001010100001100100001 <
b10000111011001010100001100100001 N
1=
1?
b10001001000100011001101000100 >
b10001001000100011001101000100 O
0@
#25000
0X
1+
b10000111011001010100001100100001 2
b10000111011001010100001100100001 T
bx 0
bx V
1)
b10010001101000101011001111000 *
b10010001101000101011001111000 Z
17
#30000
07
b11011110101011011011111011101111 ;
b11011110101011011011111011101111 M
1:
0=
0?
#35000
1X
0.
17
#40000
07
1B
b11111010110011101100101011111110 F
b11111010110011101100101011111110 Q
b1010 A
b1010 P
0:
#45000
0X
b11111010110011101100101011111110 #
b11111010110011101100101011111110 \
1&
b1010 '
b1010 [
17
#50000
07
18
b11011100101110100100001100100001 4
b11011100101110100100001100100001 J
b10101011110011010001001000110100 3
b10101011110011010001001000110100 I
1C
1D
b10 H
b10 S
b1 G
b1 R
0B
#55000
1X
1$
1%
b10 !
b10 ^
b1 "
b1 ]
0.
17
#60000
07
08
0D
0C
#65000
0X
17
#70000
07
#75000
1X
17
