RISC-V_PE/BusArbiter.v
module bus_arbiter (
    input clk,
    input reset,
    input [3:0] req,       // Request signals from the PEs. 
    output reg [3:0] grant // Grant signals for the PEs
);
    reg [1:0] current;     // Keeps track of which PE has the current priority. Scale for more PEs

    always @(posedge clk or posedge reset) begin
        if (reset) begin
            grant <= 4'b0000;
            current <= 2'b00;
        end else begin
            case (current)
                2'b00: grant <= req[0] ? 4'b0001 : (req[1] ? 4'b0010 : (req[2] ? 4'b0100 : (req[3] ? 4'b1000 : 4'b0000)));
                2'b01: grant <= req[1] ? 4'b0010 : (req[2] ? 4'b0100 : (req[3] ? 4'b1000 : (req[0] ? 4'b0001 : 4'b0000)));
                2'b10: grant <= req[2] ? 4'b0100 : (req[3] ? 4'b1000 : (req[0] ? 4'b0001 : (req[1] ? 4'b0010 : 4'b0000)));
                2'b11: grant <= req[3] ? 4'b1000 : (req[0] ? 4'b0001 : (req[1] ? 4'b0010 : (req[2] ? 4'b0100 : 4'b0000)));
            endcase

            if (req[current]) begin
                current <= current + 1;
            end
        end
    end
endmodule

RISC-V_PE/BusArbiterTB.v
`include "BusArbiter.v"

`timescale 1ns / 1ps

module tb_bus_arbiter;

    // Testbench signals
    reg clk;
    reg reset;
    reg [3:0] req;         // Request signals from PEs
    wire [3:0] grant;      // Grant signals from arbiter

    // Instantiate the arbiter module
    bus_arbiter uut (
        .clk(clk),
        .reset(reset),
        .req(req),
        .grant(grant)
    );

    // Clock generation
    initial begin
        clk = 0;
        forever #5 clk = ~clk; // Clock period = 10 time units
    end

    // Testbench logic
    initial begin
        // Dump waveform for debugging
        $dumpfile("tb_bus_arbiter.vcd");
        $dumpvars(0, tb_bus_arbiter);

        // Monitor outputs
        $monitor("Time: %0dns | grant: %b", 
                 $time, grant);


        // Initialize signals
        reset = 1;
        req = 4'b0000; // No requests initially
        #10 reset = 0; // Release reset

        // Test Case 1: Single PE requests (PE 0)
        #10 req = 4'b0001; // PE 0 requests access
        #10 req = 4'b0000; // Clear request

        // Test Case 2: Multiple requests (PE 1 and PE 3)
        #10 req = 4'b1010; // PE 1 and PE 3 request access

        // Test Case 3: Sequential requests
        #10 req = 4'b0100; // PE 2 requests access
        #10 req = 4'b0010; // PE 1 requests access

        // Test Case 4: All PEs request access
        #10 req = 4'b1111; // All PEs request access

        // Test Case 5: No requests
        #10 req = 4'b0000; // No PEs request access

        // Test Case 6: Persistent request (PE 0 keeps requesting access)
        #10 req = 4'b0001; // PE 0 requests access again
        #50 req = 4'b0000; // Clear request

        // End simulation
        #10 $finish;
    end

endmodule

RISC-V_PE/tb_bus_arbiter.vcd
$date
	Wed Mar 26 23:17:55 2025
$end
$version
	Icarus Verilog
$end
$timescale
	1ps
$end
$scope module tb_bus_arbiter $end
$var wire 4 ! grant [3:0] $end
$var reg 1 " clk $end
$var reg 4 # req [3:0] $end
$var reg 1 $ reset $end
$scope module uut $end
$var wire 1 " clk $end
$var wire 4 % req [3:0] $end
$var wire 1 $ reset $end
$var reg 2 & current [1:0] $end
$var reg 4 ' grant [3:0] $end
$upscope $end
$upscope $end
$enddefinitions $end
$comment Show the parameter values. $end
$dumpall
$end
#0
$dumpvars
b0 '
b0 &
b0 %
1$
b0 #
0"
b0 !
$end
#5000
1"
#10000
0"
0$
#15000
1"
#20000
0"
b1 #
b1 %
#25000
b1 &
b1 !
b1 '
1"
#30000
0"
b0 #
b0 %
#35000
b0 !
b0 '
1"
#40000
0"
b1010 #
b1010 %
#45000
b10 &
b10 !
b10 '
1"
#50000
0"
b100 #
b100 %
#55000
b11 &
b100 !
b100 '
1"
#60000
0"
b10 #
b10 %
#65000
b10 !
b10 '
1"
#70000
0"
b1111 #
b1111 %
#75000
b0 &
b1000 !
b1000 '
1"
#80000
0"
b0 #
b0 %
#85000
b0 !
b0 '
1"
#90000
0"
b1 #
b1 %
#95000
b1 &
b1 !
b1 '
1"
#100000
0"
#105000
1"
#110000
0"
#115000
1"
#120000
0"
#125000
1"
#130000
0"
#135000
1"
#140000
0"
b0 #
b0 %
#145000
b0 !
b0 '
1"
