RISC-V_PE/demux1_32.v
module demux1_32 (
    input      [31:0] data_in,
    output reg [31:0] out_1,
    output reg [31:0] out_2,
    output reg [31:0] out_3,
    output reg [31:0] out_4,
    output reg [31:0] out_5,
    output reg [31:0] out_6,
    output reg [31:0] out_7,
    output reg [31:0] out_8,
    output reg [31:0] out_9,
    output reg [31:0] out_10,
    output reg [31:0] out_11,
    output reg [31:0] out_12,
    output reg [31:0] out_13,
    output reg [31:0] out_14,
    output reg [31:0] out_15,
    output reg [31:0] out_16,
    output reg [31:0] out_17,
    output reg [31:0] out_18,
    output reg [31:0] out_19,
    output reg [31:0] out_20,
    output reg [31:0] out_21,
    output reg [31:0] out_22,
    output reg [31:0] out_23,
    output reg [31:0] out_24,
    output reg [31:0] out_25,
    output reg [31:0] out_26,
    output reg [31:0] out_27,
    output reg [31:0] out_28,
    output reg [31:0] out_29,
    output reg [31:0] out_30,
    output reg [31:0] out_31,
    output reg [31:0] out_32,
    input      [4:0]  sel
);
    always @(*) begin
        case(sel)
            5'b00000: out_1 = data_in; 
            5'b00001: out_2 = data_in; 
            5'b00010: out_3 = data_in; 
            5'b00011: out_4 = data_in; 
            5'b00100: out_5 = data_in; 
            5'b00101: out_6 = data_in; 
            5'b00110: out_7 = data_in; 
            5'b00111: out_8 = data_in; 
            5'b01000: out_9 = data_in; 
            5'b01001: out_10 = data_in; 
            5'b01010: out_11 = data_in; 
            5'b01011: out_12 = data_in; 
            5'b01100: out_13 = data_in; 
            5'b01101: out_14 = data_in; 
            5'b01110: out_15 = data_in; 
            5'b01111: out_16 = data_in; 
            5'b10000: out_17 = data_in; 
            5'b10001: out_18 = data_in; 
            5'b10010: out_19 = data_in; 
            5'b10011: out_20 = data_in; 
            5'b10100: out_21 = data_in; 
            5'b10101: out_22 = data_in; 
            5'b10110: out_23 = data_in; 
            5'b10111: out_24 = data_in; 
            5'b11000: out_25 = data_in; 
            5'b11001: out_26 = data_in; 
            5'b11010: out_27 = data_in; 
            5'b11011: out_28 = data_in; 
            5'b11100: out_29 = data_in; 
            5'b11101: out_30 = data_in; 
            5'b11110: out_31 = data_in; 
            5'b11111: out_32 = data_in; 
        endcase
    end

endmodule

RISC-V_PE/demux1_32TB.v
// Demux 1_32 Testbench

`include "demux1_32.v"

`timescale 1ns / 1ps

module tb_demux1_32;

    // Testbench signals
    reg [31:0] data_in;              // Input data
    reg [4:0] sel;                   // 5-bit selection signal
    wire [31:0] out_1, out_2, out_3, out_4, out_5, out_6, out_7, out_8, 
                out_9, out_10, out_11, out_12, out_13, out_14, out_15, out_16,
                out_17, out_18, out_19, out_20, out_21, out_22, out_23, out_24,
                out_25, out_26, out_27, out_28, out_29, out_30, out_31, out_32;

    // Instantiate the demux1_32 module
    demux1_32 uut (
        .data_in(data_in),
        .sel(sel),
        .out_1(out_1), .out_2(out_2), .out_3(out_3), .out_4(out_4), 
        .out_5(out_5), .out_6(out_6), .out_7(out_7), .out_8(out_8), 
        .out_9(out_9), .out_10(out_10), .out_11(out_11), .out_12(out_12), 
        .out_13(out_13), .out_14(out_14), .out_15(out_15), .out_16(out_16),
        .out_17(out_17), .out_18(out_18), .out_19(out_19), .out_20(out_20), 
        .out_21(out_21), .out_22(out_22), .out_23(out_23), .out_24(out_24),
        .out_25(out_25), .out_26(out_26), .out_27(out_27), .out_28(out_28),
        .out_29(out_29), .out_30(out_30), .out_31(out_31), .out_32(out_32)
    );

    // Initialize and run the simulation
    initial begin
        // Dump waveforms for debugging
        $dumpfile("tb_demux1_32.vcd");
        $dumpvars(0, tb_demux1_32);

        // Test all selection lines
        data_in = 32'hA5A5A5A5; // Example data pattern
        sel = 0; // Initialize selection

        // Iterate through all possible sel values
        repeat (32) begin
            #10; // Wait for 10 time units
            data_in = data_in + 1;
            $display("SEL=%d: out_1=%h, out_2=%h, out_3=%h, out_4=%h, out_5=%h, out_6=%h, out_7=%h, out_8=%h, out_9=%h, out_10=%h, out_11=%h, out_12=%h, out_13=%h, out_14=%h, out_15=%h, out_16=%h, out_17=%h, out_18=%h, out_19=%h, out_20=%h, out_21=%h, out_22=%h, out_23=%h, out_24=%h, out_25=%h, out_26=%h, out_27=%h, out_28=%h, out_29=%h, out_30=%h, out_31=%h, out_32=%h", 
                     sel, out_1, out_2, out_3, out_4, out_5, out_6, out_7, out_8, out_9, out_10, out_11, out_12, out_13, out_14, out_15, out_16, out_17, out_18, out_19, out_20, out_21, out_22, out_23, out_24, out_25, out_26, out_27, out_28, out_29, out_30, out_31, out_32);
            sel = sel + 1; // Increment selection
            $display("##########################################################################");
        end

        $finish; // End simulation
    end

endmodule

RISC-V_PE/tb_demux1_32.vcd
$date
	Thu Mar 20 17:27:29 2025
$end
$version
	Icarus Verilog
$end
$timescale
	1ps
$end
$scope module tb_demux1_32 $end
$var wire 32 ! out_9 [31:0] $end
$var wire 32 " out_8 [31:0] $end
$var wire 32 # out_7 [31:0] $end
$var wire 32 $ out_6 [31:0] $end
$var wire 32 % out_5 [31:0] $end
$var wire 32 & out_4 [31:0] $end
$var wire 32 ' out_32 [31:0] $end
$var wire 32 ( out_31 [31:0] $end
$var wire 32 ) out_30 [31:0] $end
$var wire 32 * out_3 [31:0] $end
$var wire 32 + out_29 [31:0] $end
$var wire 32 , out_28 [31:0] $end
$var wire 32 - out_27 [31:0] $end
$var wire 32 . out_26 [31:0] $end
$var wire 32 / out_25 [31:0] $end
$var wire 32 0 out_24 [31:0] $end
$var wire 32 1 out_23 [31:0] $end
$var wire 32 2 out_22 [31:0] $end
$var wire 32 3 out_21 [31:0] $end
$var wire 32 4 out_20 [31:0] $end
$var wire 32 5 out_2 [31:0] $end
$var wire 32 6 out_19 [31:0] $end
$var wire 32 7 out_18 [31:0] $end
$var wire 32 8 out_17 [31:0] $end
$var wire 32 9 out_16 [31:0] $end
$var wire 32 : out_15 [31:0] $end
$var wire 32 ; out_14 [31:0] $end
$var wire 32 < out_13 [31:0] $end
$var wire 32 = out_12 [31:0] $end
$var wire 32 > out_11 [31:0] $end
$var wire 32 ? out_10 [31:0] $end
$var wire 32 @ out_1 [31:0] $end
$var reg 32 A data_in [31:0] $end
$var reg 5 B sel [4:0] $end
$scope module uut $end
$var wire 32 C data_in [31:0] $end
$var wire 5 D sel [4:0] $end
$var reg 32 E out_1 [31:0] $end
$var reg 32 F out_10 [31:0] $end
$var reg 32 G out_11 [31:0] $end
$var reg 32 H out_12 [31:0] $end
$var reg 32 I out_13 [31:0] $end
$var reg 32 J out_14 [31:0] $end
$var reg 32 K out_15 [31:0] $end
$var reg 32 L out_16 [31:0] $end
$var reg 32 M out_17 [31:0] $end
$var reg 32 N out_18 [31:0] $end
$var reg 32 O out_19 [31:0] $end
$var reg 32 P out_2 [31:0] $end
$var reg 32 Q out_20 [31:0] $end
$var reg 32 R out_21 [31:0] $end
$var reg 32 S out_22 [31:0] $end
$var reg 32 T out_23 [31:0] $end
$var reg 32 U out_24 [31:0] $end
$var reg 32 V out_25 [31:0] $end
$var reg 32 W out_26 [31:0] $end
$var reg 32 X out_27 [31:0] $end
$var reg 32 Y out_28 [31:0] $end
$var reg 32 Z out_29 [31:0] $end
$var reg 32 [ out_3 [31:0] $end
$var reg 32 \ out_30 [31:0] $end
$var reg 32 ] out_31 [31:0] $end
$var reg 32 ^ out_32 [31:0] $end
$var reg 32 _ out_4 [31:0] $end
$var reg 32 ` out_5 [31:0] $end
$var reg 32 a out_6 [31:0] $end
$var reg 32 b out_7 [31:0] $end
$var reg 32 c out_8 [31:0] $end
$var reg 32 d out_9 [31:0] $end
$upscope $end
$upscope $end
$enddefinitions $end
$comment Show the parameter values. $end
$dumpall
$end
#0
$dumpvars
bx d
bx c
bx b
bx a
bx `
bx _
bx ^
bx ]
bx \
bx [
bx Z
bx Y
bx X
bx W
bx V
bx U
bx T
bx S
bx R
bx Q
bx P
bx O
bx N
bx M
bx L
bx K
bx J
bx I
bx H
bx G
bx F
b10100101101001011010010110100101 E
b0 D
b10100101101001011010010110100101 C
b0 B
b10100101101001011010010110100101 A
b10100101101001011010010110100101 @
bx ?
bx >
bx =
bx <
bx ;
bx :
bx 9
bx 8
bx 7
bx 6
bx 5
bx 4
bx 3
bx 2
bx 1
bx 0
bx /
bx .
bx -
bx ,
bx +
bx *
bx )
bx (
bx '
bx &
bx %
bx $
bx #
bx "
bx !
$end
#10000
b10100101101001011010010110100110 5
b10100101101001011010010110100110 P
b1 B
b1 D
b10100101101001011010010110100110 A
b10100101101001011010010110100110 C
#20000
b10100101101001011010010110100111 *
b10100101101001011010010110100111 [
b10 B
b10 D
b10100101101001011010010110100111 A
b10100101101001011010010110100111 C
#30000
b10100101101001011010010110101000 &
b10100101101001011010010110101000 _
b11 B
b11 D
b10100101101001011010010110101000 A
b10100101101001011010010110101000 C
#40000
b10100101101001011010010110101001 %
b10100101101001011010010110101001 `
b100 B
b100 D
b10100101101001011010010110101001 A
b10100101101001011010010110101001 C
#50000
b10100101101001011010010110101010 $
b10100101101001011010010110101010 a
b101 B
b101 D
b10100101101001011010010110101010 A
b10100101101001011010010110101010 C
#60000
b10100101101001011010010110101011 #
b10100101101001011010010110101011 b
b110 B
b110 D
b10100101101001011010010110101011 A
b10100101101001011010010110101011 C
#70000
b10100101101001011010010110101100 "
b10100101101001011010010110101100 c
b111 B
b111 D
b10100101101001011010010110101100 A
b10100101101001011010010110101100 C
#80000
b10100101101001011010010110101101 !
b10100101101001011010010110101101 d
b1000 B
b1000 D
b10100101101001011010010110101101 A
b10100101101001011010010110101101 C
#90000
b10100101101001011010010110101110 ?
b10100101101001011010010110101110 F
b1001 B
b1001 D
b10100101101001011010010110101110 A
b10100101101001011010010110101110 C
#100000
b10100101101001011010010110101111 >
b10100101101001011010010110101111 G
b1010 B
b1010 D
b10100101101001011010010110101111 A
b10100101101001011010010110101111 C
#110000
b10100101101001011010010110110000 =
b10100101101001011010010110110000 H
b1011 B
b1011 D
b10100101101001011010010110110000 A
b10100101101001011010010110110000 C
#120000
b10100101101001011010010110110001 <
b10100101101001011010010110110001 I
b1100 B
b1100 D
b10100101101001011010010110110001 A
b10100101101001011010010110110001 C
#130000
b10100101101001011010010110110010 ;
b10100101101001011010010110110010 J
b1101 B
b1101 D
b10100101101001011010010110110010 A
b10100101101001011010010110110010 C
#140000
b10100101101001011010010110110011 :
b10100101101001011010010110110011 K
b1110 B
b1110 D
b10100101101001011010010110110011 A
b10100101101001011010010110110011 C
#150000
b10100101101001011010010110110100 9
b10100101101001011010010110110100 L
b1111 B
b1111 D
b10100101101001011010010110110100 A
b10100101101001011010010110110100 C
#160000
b10100101101001011010010110110101 8
b10100101101001011010010110110101 M
b10000 B
b10000 D
b10100101101001011010010110110101 A
b10100101101001011010010110110101 C
#170000
b10100101101001011010010110110110 7
b10100101101001011010010110110110 N
b10001 B
b10001 D
b10100101101001011010010110110110 A
b10100101101001011010010110110110 C
#180000
b10100101101001011010010110110111 6
b10100101101001011010010110110111 O
b10010 B
b10010 D
b10100101101001011010010110110111 A
b10100101101001011010010110110111 C
#190000
b10100101101001011010010110111000 4
b10100101101001011010010110111000 Q
b10011 B
b10011 D
b10100101101001011010010110111000 A
b10100101101001011010010110111000 C
#200000
b10100101101001011010010110111001 3
b10100101101001011010010110111001 R
b10100 B
b10100 D
b10100101101001011010010110111001 A
b10100101101001011010010110111001 C
#210000
b10100101101001011010010110111010 2
b10100101101001011010010110111010 S
b10101 B
b10101 D
b10100101101001011010010110111010 A
b10100101101001011010010110111010 C
#220000
b10100101101001011010010110111011 1
b10100101101001011010010110111011 T
b10110 B
b10110 D
b10100101101001011010010110111011 A
b10100101101001011010010110111011 C
#230000
b10100101101001011010010110111100 0
b10100101101001011010010110111100 U
b10111 B
b10111 D
b10100101101001011010010110111100 A
b10100101101001011010010110111100 C
#240000
b10100101101001011010010110111101 /
b10100101101001011010010110111101 V
b11000 B
b11000 D
b10100101101001011010010110111101 A
b10100101101001011010010110111101 C
#250000
b10100101101001011010010110111110 .
b10100101101001011010010110111110 W
b11001 B
b11001 D
b10100101101001011010010110111110 A
b10100101101001011010010110111110 C
#260000
b10100101101001011010010110111111 -
b10100101101001011010010110111111 X
b11010 B
b11010 D
b10100101101001011010010110111111 A
b10100101101001011010010110111111 C
#270000
b10100101101001011010010111000000 ,
b10100101101001011010010111000000 Y
b11011 B
b11011 D
b10100101101001011010010111000000 A
b10100101101001011010010111000000 C
#280000
b10100101101001011010010111000001 +
b10100101101001011010010111000001 Z
b11100 B
b11100 D
b10100101101001011010010111000001 A
b10100101101001011010010111000001 C
#290000
b10100101101001011010010111000010 )
b10100101101001011010010111000010 \
b11101 B
b11101 D
b10100101101001011010010111000010 A
b10100101101001011010010111000010 C
#300000
b10100101101001011010010111000011 (
b10100101101001011010010111000011 ]
b11110 B
b11110 D
b10100101101001011010010111000011 A
b10100101101001011010010111000011 C
#310000
b10100101101001011010010111000100 '
b10100101101001011010010111000100 ^
b11111 B
b11111 D
b10100101101001011010010111000100 A
b10100101101001011010010111000100 C
#320000
b10100101101001011010010111000101 @
b10100101101001011010010111000101 E
b0 B
b0 D
b10100101101001011010010111000101 A
b10100101101001011010010111000101 C
